{
    "products": [
      {
        "type": "honey",
        "items": [
          {
            "titre": "Miel de Lavande",
            "description": "Origine: Provence, France. Arôme envoûtant de lavande. Texture crémeuse et délicate.",
            "image": "assets/images/honey-products.webp",
            "alt": "image pot de miel",
            "prix": 25
          },
          {
            "titre": "Miel de Lavande",
            "description": "Origine: Provence, France. Arôme envoûtant de lavande. Texture crémeuse et délicate.",
            "image": "assets/images/honey-products.webp",
            "alt": "image pot de miel",
            "prix": 25
          },
          {
            "titre": "Miel d'Acacia",
            "description": "Origine: Roumanie. Douceur exceptionnelle avec des notes légères de vanille. Parfait pour sucrer vos boissons.",
            "image": "assets/images/honey-products.webp",
            "alt": "image pot de miel",
            "prix": 18
          },
          {
            "titre": "Miel d'Acacia",
            "description": "Origine: Roumanie. Douceur exceptionnelle avec des notes légères de vanille. Parfait pour sucrer vos boissons.",
            "image": "assets/images/honey-products.webp",
            "alt": "image pot de miel",
            "prix": 18
          },
          {
            "titre": "Miel d'Acacia",
            "description": "Origine: Roumanie. Douceur exceptionnelle avec des notes légères de vanille. Parfait pour sucrer vos boissons.",
            "image": "assets/images/honey-products.webp",
            "alt": "image pot de miel",
            "prix": 18
          },
          {
            "titre": "Miel d'Acacia",
            "description": "Origine: Roumanie. Douceur exceptionnelle avec des notes légères de vanille. Parfait pour sucrer vos boissons.",
            "image": "assets/images/honey-products.webp",
            "alt": "image pot de miel",
            "prix": 18
          }
        ]
      },
      {
        "type": "oil",
        "items": [
          {
            "titre": "Huile de Lavande",
            "description": "Origine: Provence, France. Huile essentielle extraite de la lavande. Propriétés apaisantes et parfum relaxant.",
            "image": "assets/images/oil.webp",
            "alt": "image huile 100% bio",
            "prix": 30
          },
          {
            "titre": "Huile de Lavande",
            "description": "Origine: Provence, France. Huile essentielle extraite de la lavande. Propriétés apaisantes et parfum relaxant.",
            "image": "assets/images/oil.webp",
            "alt": "image huile 100% bio",
            "prix": 30
          },
          {
            "titre": "Huile de Lavande",
            "description": "Origine: Provence, France. Huile essentielle extraite de la lavande. Propriétés apaisantes et parfum relaxant.",
            "image": "assets/images/oil.webp",
            "alt": "image huile 100% bio",
            "prix": 30
          },
          {
            "titre": "Huile de Lavande",
            "description": "Origine: Provence, France. Huile essentielle extraite de la lavande. Propriétés apaisantes et parfum relaxant.",
            "image": "assets/images/oil.webp",
            "alt": "image huile 100% bio",
            "prix": 30
          },
          {
            "titre": "Huile de Lavande",
            "description": "Origine: Provence, France. Huile essentielle extraite de la lavande. Propriétés apaisantes et parfum relaxant.",
            "image": "assets/images/oil.webp",
            "alt": "image huile 100% bio",
            "prix": 30
          },
          {
            "titre": "Huile de Lavande",
            "description": "Origine: Provence, France. Huile essentielle extraite de la lavande. Propriétés apaisantes et parfum relaxant.",
            "image": "assets/images/oil.webp",
            "alt": "image huile 100% bio",
            "prix": 30
          }
        ]
      },
      {
        "type": "packs",
        "items": [
          {
            "titre": "Pack booster +",
            "description": "Avec son miel à la nigelle, l'huile de nigelle et herbe de provence ce pack booster vous aidera à rester évéillé toute la journée",
            "image": "assets/images/honey-products-2.webp",
            "alt": "image pack santé +",
            "prix": 30
          },
          {
            "titre": "Pack booster +",
            "description": "Avec son miel à la nigelle, l'huile de nigelle et herbe de provence ce pack booster vous aidera à rester évéillé toute la journée",
            "image": "assets/images/honey-products-2.webp",
            "alt": "image pack santé +",
            "prix": 30
          },
          {
            "titre": "Pack booster +",
            "description": "Avec son miel à la nigelle, l'huile de nigelle et herbe de provence ce pack booster vous aidera à rester évéillé toute la journée",
            "image": "assets/images/honey-products-2.webp",
            "alt": "image pack santé +",
            "prix": 30
          },
          {
            "titre": "Pack booster +",
            "description": "Avec son miel à la nigelle, l'huile de nigelle et herbe de provence ce pack booster vous aidera à rester évéillé toute la journée",
            "image": "assets/images/honey-products-2.webp",
            "alt": "image pack santé +",
            "prix": 30
          },
          {
            "titre": "Pack booster +",
            "description": "Avec son miel à la nigelle, l'huile de nigelle et herbe de provence ce pack booster vous aidera à rester évéillé toute la journée",
            "image": "assets/images/honey-products-2.webp",
            "alt": "image pack santé +",
            "prix": 30
          },
          {
            "titre": "Pack booster +",
            "description": "Avec son miel à la nigelle, l'huile de nigelle et herbe de provence ce pack booster vous aidera à rester évéillé toute la journée",
            "image": "assets/images/honey-products-2.webp",
            "alt": "image pack santé +",
            "prix": 30
          }
        ]
      }
    ]
  }